{
  "name": "freedom-social-email",
  "description": "Email social provider for freedom.js",
  "app": {
    "script": [
      "forge.min.js",
      "compressionWorker.js",
      "browserbox-imap.js",
      "browserbox.js",
      "smtp-connection.js",
      "freedom-social-email.js",
      "email-auth.js"
    ]
  },
  "default": "social",
  "provides": [
    "social"
  ],
  "permissions": [
    "core.tcpsocket",
    "core.view"
  ],
  "views": {
    "email-login": {
      "main": "email-view.html",
      "files": [ "email-view.js" ]
    }
  }
}
